{"data":{"data":{"files":[{"file":{"fields":{"slug":"/callouts/"},"frontmatter":{"title":"Callouts"}},"fields":{"gitLogLatestAuthorName":"James Calcaben","gitLogLatestDate":"0"},"name":"callouts"},{"file":{"fields":{"slug":"/normal-markdown/"},"frontmatter":{"title":""}},"fields":{"gitLogLatestAuthorName":"James Calcaben","gitLogLatestDate":"0"},"name":"normal-markdown"},{"file":{"fields":{"slug":"/_includes/re-usable-content/"},"frontmatter":{"title":""}},"fields":{"gitLogLatestAuthorName":"hguthrie","gitLogLatestDate":"0"},"name":"re-usable-content"},{"file":{"fields":{"slug":"/cloud/mermaid/"},"frontmatter":{"title":""}},"fields":{"gitLogLatestAuthorName":"hguthrie","gitLogLatestDate":"0"},"name":"mermaid"},{"file":{"fields":{"slug":"/cloud/cloud-table/"},"frontmatter":{"title":""}},"fields":{"gitLogLatestAuthorName":"hguthrie","gitLogLatestDate":"2"},"name":"cloud-table"},{"file":{"fields":{"slug":"/cloud/cloud-architecture/"},"frontmatter":{"title":""}},"fields":{"gitLogLatestAuthorName":"hguthrie","gitLogLatestDate":"2"},"name":"cloud-architecture"},{"file":{"fields":{"slug":"/cloud/cloud-intro/"},"frontmatter":{"title":""}},"fields":{"gitLogLatestAuthorName":"hguthrie","gitLogLatestDate":"2"},"name":"cloud-intro"},{"file":{"fields":{"slug":"/navigation/navigation/"},"frontmatter":{"title":""}},"fields":{"gitLogLatestAuthorName":"hguthrie","gitLogLatestDate":"2"},"name":"navigation"},{"file":{"fields":{"slug":"/example/"},"frontmatter":{"title":""}},"fields":{"gitLogLatestAuthorName":"James Calcaben","gitLogLatestDate":"5"},"name":"example"},{"file":{"fields":{"slug":"/diagrams/"},"frontmatter":{"title":"Diagrams example"}},"fields":{"gitLogLatestAuthorName":"James Calcaben","gitLogLatestDate":"6"},"name":"diagrams"},{"file":{"fields":{"slug":"/import-mdx/"},"frontmatter":{"title":"Write and reuse"}},"fields":{"gitLogLatestAuthorName":"hguthrie","gitLogLatestDate":"35"},"name":"import-mdx"},{"file":{"fields":{"slug":"/setup/"},"frontmatter":{"title":"Setup environment"}},"fields":{"gitLogLatestAuthorName":"hguthrie","gitLogLatestDate":"35"},"name":"setup"},{"file":{"fields":{"slug":"/variables/"},"frontmatter":{"title":"Setup global variables"}},"fields":{"gitLogLatestAuthorName":"hguthrie","gitLogLatestDate":"35"},"name":"variables"},{"file":{"fields":{"slug":"/workflow/"},"frontmatter":{"title":"Begin writing"}},"fields":{"gitLogLatestAuthorName":"hguthrie","gitLogLatestDate":"35"},"name":"workflow"},{"file":{"fields":{"slug":"/nested/page/"},"frontmatter":{"title":""}},"fields":{"gitLogLatestAuthorName":"James Calcaben","gitLogLatestDate":"40"},"name":"page"}]}}}